sphinxcontrib_drf/__init__.py
sphinxcontrib_drf/docstrings/__init__.py
sphinxcontrib_drf/docstrings/classes.py
sphinxcontrib_drf/docstrings/config.py
sphinxcontrib_drf-0.1.1.dist-info/METADATA
sphinxcontrib_drf-0.1.1.dist-info/WHEEL
sphinxcontrib_drf-0.1.1.dist-info/RECORD
