Metadata-Version: 2.1
Name: sphinxcontrib-drf
Version: 0.1.1
Summary: 
Author: Bulat Kurbanov
Author-email: kurbanovbul@gmail.com
Requires-Python: >=3.10,<4.0
Classifier: Programming Language :: Python :: 3
Classifier: Programming Language :: Python :: 3.10
Classifier: Programming Language :: Python :: 3.11
Requires-Dist: django (>=3.1.6,<4.0.0)
Requires-Dist: djangorestframework (>=3.14.0,<4.0.0)
Requires-Dist: sphinx (>=6.1.3,<7.0.0)
